{"data":{"chartData":{"orderbookId":"TX5372138","assetClass":"SHARES","isin":"SE0020388577","symbol":"CINPHA","company":"Cinclus Pharma Holding","timeAsOf":"2025-11-13","lastSalePrice":"SEK 17.60","netChange":"-0.1799","percentageChange":"-1.01%","deltaIndicator":"down","previousClose":"SEK 17.78"},"charts":{"headers":{"dateTime":"Date","bid":"Bid","ask":"Ask","open":"Opening price","high":"High price","low":"Low price","close":"Closing price","average":"Average price","totalVolume":"Total volume","turnover":"Turnover","trades":"Trades"},"rows":[{"dateTime":"2025-11-13","bid":"17.50","ask":"17.82","open":"17.98","high":"18.10","low":"17.30","close":"17.78","average":"17.6352","totalVolume":"17,038","turnover":"300,467.26","trades":"71"},{"dateTime":"2025-11-12","bid":"17.60","ask":"17.98","open":"18.24","high":"18.50","low":"17.72","close":"17.98","average":"18.1343","totalVolume":"44,809","turnover":"812,588.02","trades":"108"},{"dateTime":"2025-11-11","bid":"18.20","ask":"18.32","open":"18.16","high":"18.48","low":"17.92","close":"18.22","average":"18.1612","totalVolume":"48,141","turnover":"874,298.06","trades":"127"},{"dateTime":"2025-11-10","bid":"18.08","ask":"18.16","open":"17.86","high":"18.46","low":"17.62","close":"18.16","average":"18.1349","totalVolume":"56,691","turnover":"1,028,072.1","trades":"141"},{"dateTime":"2025-11-07","bid":"17.18","ask":"17.46","open":"17.98","high":"17.98","low":"17.06","close":"17.44","average":"17.3421","totalVolume":"28,165","turnover":"488,478.51","trades":"76"},{"dateTime":"2025-11-06","bid":"17.00","ask":"17.50","open":"17.00","high":"17.96","low":"16.72","close":"17.48","average":"17.2083","totalVolume":"125,728","turnover":"2,163,661.62","trades":"280"},{"dateTime":"2025-11-05","bid":"17.04","ask":"17.26","open":"17.54","high":"17.80","low":"16.70","close":"17.24","average":"17.0582","totalVolume":"87,532","turnover":"1,493,448.95","trades":"152"},{"dateTime":"2025-11-04","bid":"17.06","ask":"17.54","open":"16.78","high":"17.96","low":"16.38","close":"17.54","average":"16.7369","totalVolume":"68,999","turnover":"1,154,847.14","trades":"142"},{"dateTime":"2025-11-03","bid":"16.82","ask":"17.00","open":"16.60","high":"17.00","low":"16.38","close":"16.94","average":"16.6488","totalVolume":"20,718","turnover":"344,928.51","trades":"95"},{"dateTime":"2025-10-31","bid":"16.08","ask":"16.52","open":"16.20","high":"16.62","low":"15.82","close":"16.40","average":"16.2669","totalVolume":"10,482","turnover":"170,509.76","trades":"57"},{"dateTime":"2025-10-30","bid":"16.20","ask":"16.32","open":"16.16","high":"16.64","low":"15.92","close":"16.30","average":"16.1579","totalVolume":"15,518","turnover":"250,744.05","trades":"119"},{"dateTime":"2025-10-29","bid":"16.16","ask":"16.66","open":"16.48","high":"16.94","low":"15.70","close":"16.62","average":"16.113","totalVolume":"48,786","turnover":"786,905.85","trades":"197"},{"dateTime":"2025-10-28","bid":"15.92","ask":"16.28","open":"16.30","high":"16.38","low":"15.90","close":"16.24","average":"16.1629","totalVolume":"8,427","turnover":"136,224.88","trades":"72"},{"dateTime":"2025-10-27","bid":"16.00","ask":"16.26","open":"16.74","high":"16.74","low":"15.84","close":"16.22","average":"16.1941","totalVolume":"25,890","turnover":"419,284","trades":"109"},{"dateTime":"2025-10-24","bid":"16.30","ask":"16.40","open":"15.70","high":"16.48","low":"15.70","close":"16.38","average":"16.049","totalVolume":"42,893","turnover":"688,347.97","trades":"140"},{"dateTime":"2025-10-23","bid":"15.60","ask":"15.98","open":"16.06","high":"16.26","low":"15.34","close":"15.98","average":"15.6405","totalVolume":"32,343","turnover":"505,762.05","trades":"123"},{"dateTime":"2025-10-22","bid":"16.00","ask":"16.06","open":"16.12","high":"16.12","low":"15.58","close":"15.76","average":"15.7829","totalVolume":"31,662","turnover":"499,675.49","trades":"74"},{"dateTime":"2025-10-21","bid":"15.60","ask":"15.88","open":"15.92","high":"16.44","low":"15.42","close":"15.66","average":"15.9155","totalVolume":"131,830","turnover":"2,098,989.04","trades":"242"},{"dateTime":"2025-10-20","bid":"15.66","ask":"16.12","open":"16.28","high":"16.28","low":"15.24","close":"15.24","average":"15.6281","totalVolume":"42,051","turnover":"657,318.73","trades":"91"},{"dateTime":"2025-10-17","bid":"15.94","ask":"16.12","open":"16.60","high":"16.60","low":"15.72","close":"15.74","average":"15.9076","totalVolume":"28,006","turnover":"445,665.85","trades":"101"},{"dateTime":"2025-10-16","bid":"16.18","ask":"16.60","open":"16.68","high":"16.68","low":"16.16","close":"16.16","average":"16.3078","totalVolume":"28,475","turnover":"464,372.01","trades":"87"},{"dateTime":"2025-10-15","bid":"16.50","ask":"16.60","open":"16.26","high":"16.70","low":"16.26","close":"16.38","average":"16.5128","totalVolume":"24,447","turnover":"404,003.47","trades":"113"},{"dateTime":"2025-10-14","bid":"16.22","ask":"16.42","open":"17.00","high":"17.00","low":"16.20","close":"16.20","average":"16.3181","totalVolume":"17,696","turnover":"288,785.6","trades":"86"},{"dateTime":"2025-10-13","bid":"16.74","ask":"17.48","open":"16.40","high":"17.46","low":"16.02","close":"16.56","average":"16.354","totalVolume":"35,949","turnover":"587,742.92","trades":"130"},{"dateTime":"2025-10-10","bid":"16.46","ask":"16.84","open":"17.20","high":"17.20","low":"16.46","close":"16.46","average":"16.8047","totalVolume":"36,332","turnover":"611,008.39","trades":"86"},{"dateTime":"2025-10-09","bid":"17.00","ask":"17.20","open":"17.50","high":"17.64","low":"17.00","close":"17.00","average":"17.113","totalVolume":"59,617","turnover":"1,020,242.19","trades":"106"},{"dateTime":"2025-10-08","bid":"17.16","ask":"17.50","open":"17.26","high":"17.50","low":"17.00","close":"17.14","average":"17.1646","totalVolume":"42,194","turnover":"724,263.66","trades":"149"},{"dateTime":"2025-10-07","bid":"17.16","ask":"17.42","open":"17.28","high":"17.84","low":"17.14","close":"17.24","average":"17.3579","totalVolume":"98,705","turnover":"1,713,420.74","trades":"223"},{"dateTime":"2025-10-06","bid":"17.12","ask":"17.40","open":"17.36","high":"17.88","low":"16.68","close":"16.90","average":"17.1141","totalVolume":"79,151","turnover":"1,354,423.64","trades":"210"},{"dateTime":"2025-10-03","bid":"17.16","ask":"17.36","open":"17.94","high":"17.94","low":"17.14","close":"17.34","average":"17.4463","totalVolume":"99,301","turnover":"1,732,504.53","trades":"174"},{"dateTime":"2025-10-02","bid":"17.76","ask":"17.78","open":"17.64","high":"17.96","low":"17.50","close":"17.78","average":"17.7084","totalVolume":"52,637","turnover":"932,141.76","trades":"139"},{"dateTime":"2025-10-01","bid":"17.52","ask":"17.78","open":"17.50","high":"17.78","low":"16.96","close":"17.64","average":"17.4306","totalVolume":"38,621","turnover":"673,059.15","trades":"131"},{"dateTime":"2025-09-30","bid":"17.48","ask":"17.66","open":"16.92","high":"17.78","low":"16.88","close":"17.48","average":"17.4018","totalVolume":"96,847","turnover":"1,687,119.2","trades":"198"},{"dateTime":"2025-09-29","bid":"16.54","ask":"16.88","open":"16.74","high":"16.86","low":"16.00","close":"16.86","average":"16.3213","totalVolume":"47,601","turnover":"776,660.27","trades":"136"},{"dateTime":"2025-09-26","bid":"16.34","ask":"16.84","open":"16.48","high":"16.70","low":"16.00","close":"16.04","average":"16.192","totalVolume":"90,180","turnover":"1,460,586.47","trades":"213"},{"dateTime":"2025-09-25","bid":"16.30","ask":"16.48","open":"16.42","high":"16.68","low":"16.08","close":"16.28","average":"16.3503","totalVolume":"55,829","turnover":"913,003.06","trades":"135"},{"dateTime":"2025-09-24","bid":"16.58","ask":"16.60","open":"17.06","high":"17.06","low":"16.42","close":"16.44","average":"16.7029","totalVolume":"42,002","turnover":"701,074.66","trades":"142"},{"dateTime":"2025-09-23","bid":"16.96","ask":"16.98","open":"17.40","high":"17.88","low":"16.90","close":"16.90","average":"17.3483","totalVolume":"113,927","turnover":"1,977,167.87","trades":"197"},{"dateTime":"2025-09-22","bid":"17.28","ask":"17.40","open":"17.30","high":"17.58","low":"16.96","close":"17.26","average":"17.218","totalVolume":"79,541","turnover":"1,369,673.55","trades":"149"},{"dateTime":"2025-09-19","bid":"17.30","ask":"17.38","open":"17.40","high":"17.78","low":"17.08","close":"17.16","average":"17.3526","totalVolume":"81,549","turnover":"1,414,989.21","trades":"133"},{"dateTime":"2025-09-18","bid":"17.40","ask":"17.46","open":"17.34","high":"17.90","low":"17.26","close":"17.26","average":"17.5789","totalVolume":"100,140","turnover":"1,761,052.83","trades":"192"},{"dateTime":"2025-09-17","bid":"17.18","ask":"17.34","open":"17.50","high":"17.76","low":"17.06","close":"17.16","average":"17.2516","totalVolume":"44,056","turnover":"760,109.28","trades":"173"},{"dateTime":"2025-09-16","bid":"17.08","ask":"17.18","open":"17.80","high":"17.98","low":"17.00","close":"17.00","average":"17.4256","totalVolume":"114,736","turnover":"1,999,650.81","trades":"243"},{"dateTime":"2025-09-15","bid":"17.48","ask":"17.80","open":"17.16","high":"17.86","low":"16.94","close":"17.42","average":"17.3773","totalVolume":"185,151","turnover":"3,217,645.15","trades":"303"},{"dateTime":"2025-09-12","bid":"16.90","ask":"17.22","open":"15.50","high":"17.50","low":"15.38","close":"17.16","average":"16.5174","totalVolume":"450,608","turnover":"7,440,924.95","trades":"915"},{"dateTime":"2025-09-11","bid":"15.06","ask":"15.16","open":"15.26","high":"15.30","low":"14.82","close":"15.16","average":"15.0797","totalVolume":"25,666","turnover":"387,116.74","trades":"113"},{"dateTime":"2025-09-10","bid":"15.18","ask":"15.26","open":"15.10","high":"15.48","low":"14.82","close":"14.82","average":"15.0789","totalVolume":"53,088","turnover":"800,900.93","trades":"159"},{"dateTime":"2025-09-09","bid":"15.10","ask":"15.16","open":"15.30","high":"15.32","low":"15.04","close":"15.22","average":"15.1947","totalVolume":"46,386","turnover":"704,796.32","trades":"184"},{"dateTime":"2025-09-08","bid":"15.14","ask":"15.32","open":"15.34","high":"15.64","low":"15.04","close":"15.64","average":"15.5125","totalVolume":"53,778","turnover":"833,931.95","trades":"102"},{"dateTime":"2025-09-05","bid":"15.16","ask":"15.34","open":"15.70","high":"15.70","low":"15.08","close":"15.08","average":"15.4044","totalVolume":"37,950","turnover":"584,692.75","trades":"184"},{"dateTime":"2025-09-04","bid":"15.40","ask":"15.44","open":"15.16","high":"15.68","low":"15.00","close":"15.44","average":"15.3301","totalVolume":"52,700","turnover":"807,890.56","trades":"210"},{"dateTime":"2025-09-03","bid":"15.14","ask":"15.32","open":"15.50","high":"15.52","low":"15.08","close":"15.34","average":"15.2808","totalVolume":"30,599","turnover":"467,597.9","trades":"139"},{"dateTime":"2025-09-02","bid":"15.20","ask":"15.50","open":"16.00","high":"16.26","low":"14.92","close":"15.46","average":"15.3394","totalVolume":"117,064","turnover":"1,795,513.99","trades":"256"},{"dateTime":"2025-09-01","bid":"16.00","ask":"16.16","open":"15.50","high":"16.70","low":"15.32","close":"16.08","average":"15.9582","totalVolume":"265,716","turnover":"4,239,286.93","trades":"398"},{"dateTime":"2025-08-29","bid":"15.50","ask":"15.60","open":"15.78","high":"15.96","low":"15.32","close":"15.60","average":"15.7512","totalVolume":"71,628","turnover":"1,128,321.56","trades":"253"},{"dateTime":"2025-08-28","bid":"15.48","ask":"15.58","open":"15.74","high":"15.74","low":"15.30","close":"15.44","average":"15.4837","totalVolume":"19,267","turnover":"298,353.69","trades":"123"},{"dateTime":"2025-08-27","bid":"15.68","ask":"15.70","open":"15.50","high":"15.70","low":"15.28","close":"15.70","average":"15.5474","totalVolume":"46,155","turnover":"717,639.69","trades":"196"},{"dateTime":"2025-08-26","bid":"15.56","ask":"15.76","open":"15.72","high":"15.82","low":"15.50","close":"15.58","average":"15.6353","totalVolume":"63,919","turnover":"999,299.74","trades":"122"},{"dateTime":"2025-08-25","bid":"15.62","ask":"15.70","open":"16.08","high":"16.30","low":"15.36","close":"15.66","average":"15.5944","totalVolume":"111,253","turnover":"1,734,753.42","trades":"377"},{"dateTime":"2025-08-22","bid":"15.78","ask":"16.10","open":"15.70","high":"16.16","low":"15.34","close":"16.06","average":"15.6749","totalVolume":"88,055","turnover":"1,380,195.93","trades":"341"},{"dateTime":"2025-08-21","bid":"15.80","ask":"15.82","open":"16.42","high":"16.42","low":"15.66","close":"15.82","average":"16.0363","totalVolume":"31,243","turnover":"500,996.82","trades":"165"},{"dateTime":"2025-08-20","bid":"16.42","ask":"16.46","open":"15.50","high":"16.48","low":"15.40","close":"16.46","average":"15.9473","totalVolume":"55,188","turnover":"880,279.61","trades":"221"},{"dateTime":"2025-08-19","bid":"15.50","ask":"15.62","open":"15.62","high":"16.44","low":"15.44","close":"15.50","average":"15.6253","totalVolume":"44,009","turnover":"687,803.97","trades":"160"},{"dateTime":"2025-08-18","bid":"15.62","ask":"15.70","open":"15.96","high":"16.42","low":"15.44","close":"15.60","average":"15.7331","totalVolume":"16,489","turnover":"259,615.02","trades":"113"},{"dateTime":"2025-08-15","bid":"16.04","ask":"16.10","open":"16.20","high":"16.56","low":"15.78","close":"16.16","average":"16.137","totalVolume":"36,324","turnover":"586,171.4","trades":"95"},{"dateTime":"2025-08-14","bid":"16.02","ask":"16.18","open":"15.90","high":"16.52","low":"15.70","close":"16.20","average":"16.131","totalVolume":"37,975","turnover":"612,487.23","trades":"143"},{"dateTime":"2025-08-13","bid":"16.32","ask":"16.56","open":"17.40","high":"17.40","low":"15.92","close":"16.58","average":"16.3924","totalVolume":"104,754","turnover":"1,717,622.21","trades":"248"},{"dateTime":"2025-08-12","bid":"16.84","ask":"17.00","open":"17.36","high":"17.48","low":"16.80","close":"16.88","average":"16.9773","totalVolume":"58,351","turnover":"990,771.91","trades":"156"},{"dateTime":"2025-08-11","bid":"17.16","ask":"17.36","open":"17.28","high":"17.70","low":"17.10","close":"17.36","average":"17.3538","totalVolume":"20,384","turnover":"353,828.82","trades":"117"},{"dateTime":"2025-08-08","bid":"17.10","ask":"17.26","open":"17.90","high":"18.06","low":"17.10","close":"17.28","average":"17.3718","totalVolume":"26,048","turnover":"452,435.37","trades":"134"},{"dateTime":"2025-08-07","bid":"17.36","ask":"17.64","open":"17.92","high":"18.18","low":"17.32","close":"17.60","average":"17.7463","totalVolume":"27,840","turnover":"494,063.76","trades":"113"},{"dateTime":"2025-08-06","bid":"17.60","ask":"17.92","open":"17.94","high":"18.18","low":"17.52","close":"17.96","average":"17.8372","totalVolume":"12,533","turnover":"223,572.06","trades":"98"},{"dateTime":"2025-08-05","bid":"17.62","ask":"17.76","open":"17.98","high":"17.98","low":"17.56","close":"17.78","average":"17.6857","totalVolume":"27,333","turnover":"483,460.17","trades":"114"},{"dateTime":"2025-08-04","bid":"17.42","ask":"17.68","open":"17.38","high":"17.80","low":"17.16","close":"17.48","average":"17.4298","totalVolume":"41,867","turnover":"729,872.38","trades":"163"},{"dateTime":"2025-08-01","bid":"17.18","ask":"17.38","open":"17.70","high":"17.70","low":"17.14","close":"17.18","average":"17.3432","totalVolume":"26,490","turnover":"459,404.04","trades":"108"},{"dateTime":"2025-07-31","bid":"17.46","ask":"17.68","open":"19.00","high":"19.00","low":"17.42","close":"17.46","average":"17.9625","totalVolume":"19,704","turnover":"353,987.94","trades":"111"},{"dateTime":"2025-07-30","bid":"18.34","ask":"18.52","open":"18.20","high":"19.30","low":"18.10","close":"18.32","average":"18.7118","totalVolume":"196,310","turnover":"3,674,559.71","trades":"298"},{"dateTime":"2025-07-29","bid":"18.22","ask":"18.36","open":"17.78","high":"18.50","low":"17.78","close":"18.40","average":"18.2089","totalVolume":"133,348","turnover":"2,427,923.49","trades":"276"},{"dateTime":"2025-07-28","bid":"17.78","ask":"17.86","open":"17.32","high":"18.02","low":"17.30","close":"17.86","average":"17.775","totalVolume":"41,281","turnover":"734,037.02","trades":"172"},{"dateTime":"2025-07-25","bid":"17.26","ask":"17.30","open":"17.34","high":"17.46","low":"17.12","close":"17.30","average":"17.3033","totalVolume":"9,671","turnover":"167,341.65","trades":"67"},{"dateTime":"2025-07-24","bid":"17.30","ask":"17.34","open":"17.64","high":"17.88","low":"17.12","close":"17.34","average":"17.4392","totalVolume":"38,310","turnover":"668,305.28","trades":"130"},{"dateTime":"2025-07-23","bid":"17.30","ask":"17.50","open":"17.00","high":"17.60","low":"16.86","close":"17.46","average":"17.304","totalVolume":"29,793","turnover":"515,385.11","trades":"160"},{"dateTime":"2025-07-22","bid":"16.84","ask":"17.00","open":"16.76","high":"17.28","low":"16.76","close":"17.00","average":"16.9853","totalVolume":"29,036","turnover":"493,188.32","trades":"140"},{"dateTime":"2025-07-21","bid":"16.72","ask":"16.98","open":"16.94","high":"17.00","low":"16.54","close":"16.62","average":"16.7445","totalVolume":"31,009","turnover":"519,282.92","trades":"165"},{"dateTime":"2025-07-18","bid":"16.68","ask":"16.94","open":"16.52","high":"17.00","low":"16.50","close":"16.68","average":"16.6945","totalVolume":"36,445","turnover":"608,458.07","trades":"142"},{"dateTime":"2025-07-17","bid":"16.46","ask":"16.70","open":"16.30","high":"16.84","low":"16.20","close":"16.70","average":"16.4903","totalVolume":"34,799","turnover":"573,823.62","trades":"100"},{"dateTime":"2025-07-16","bid":"16.30","ask":"16.52","open":"16.90","high":"16.96","low":"16.20","close":"16.50","average":"16.5815","totalVolume":"48,059","turnover":"796,853.33","trades":"176"},{"dateTime":"2025-07-15","bid":"16.26","ask":"16.90","open":"15.88","high":"16.90","low":"15.88","close":"16.82","average":"16.1413","totalVolume":"57,346","turnover":"925,571.35","trades":"185"},{"dateTime":"2025-07-14","bid":"15.88","ask":"16.08","open":"15.70","high":"16.24","low":"15.70","close":"15.90","average":"15.9609","totalVolume":"49,508","turnover":"790,830.65","trades":"252"},{"dateTime":"2025-07-11","bid":"15.70","ask":"15.88","open":"15.86","high":"15.96","low":"15.60","close":"15.70","average":"15.6981","totalVolume":"41,707","turnover":"654,721.46","trades":"174"},{"dateTime":"2025-07-10","bid":"15.80","ask":"15.90","open":"16.20","high":"16.20","low":"15.80","close":"15.90","average":"15.9337","totalVolume":"26,708","turnover":"425,601.68","trades":"101"},{"dateTime":"2025-07-09","bid":"16.08","ask":"16.20","open":"15.96","high":"16.28","low":"15.80","close":"16.18","average":"16.1089","totalVolume":"42,827","turnover":"689,762.03","trades":"154"},{"dateTime":"2025-07-08","bid":"15.96","ask":"16.12","open":"15.70","high":"16.26","low":"15.70","close":"16.08","average":"16.0273","totalVolume":"33,634","turnover":"538,985.1","trades":"171"},{"dateTime":"2025-07-07","bid":"15.70","ask":"15.82","open":"15.80","high":"16.18","low":"15.52","close":"15.74","average":"15.7352","totalVolume":"45,187","turnover":"711,324.62","trades":"167"},{"dateTime":"2025-07-04","bid":"15.70","ask":"15.80","open":"16.24","high":"16.24","low":"15.70","close":"15.70","average":"15.8652","totalVolume":"51,656","turnover":"819,504.06","trades":"141"},{"dateTime":"2025-07-03","bid":"16.16","ask":"16.24","open":"15.90","high":"16.32","low":"15.72","close":"16.16","average":"16.0817","totalVolume":"60,841","turnover":"978,335.67","trades":"203"},{"dateTime":"2025-07-02","bid":"15.84","ask":"15.98","open":"15.70","high":"16.02","low":"15.70","close":"15.86","average":"15.8513","totalVolume":"24,588","turnover":"389,774.23","trades":"115"},{"dateTime":"2025-07-01","bid":"15.68","ask":"15.82","open":"15.80","high":"16.22","low":"15.66","close":"15.72","average":"15.8541","totalVolume":"25,969","turnover":"411,771.3","trades":"143"},{"dateTime":"2025-06-30","bid":"15.80","ask":"16.04","open":"16.24","high":"16.24","low":"15.66","close":"15.88","average":"15.8825","totalVolume":"95,831","turnover":"1,522,027.88","trades":"260"},{"dateTime":"2025-06-27","bid":"15.86","ask":"16.08","open":"16.12","high":"16.26","low":"15.70","close":"16.04","average":"15.8777","totalVolume":"69,995","turnover":"1,111,405.34","trades":"212"},{"dateTime":"2025-06-26","bid":"16.06","ask":"16.24","open":"15.74","high":"16.26","low":"15.44","close":"16.20","average":"15.9275","totalVolume":"92,536","turnover":"1,473,309.74","trades":"285"},{"dateTime":"2025-06-25","bid":"15.74","ask":"15.86","open":"16.06","high":"16.52","low":"15.72","close":"15.74","average":"15.9393","totalVolume":"82,714","turnover":"1,318,631.21","trades":"286"},{"dateTime":"2025-06-24","bid":"16.06","ask":"16.18","open":"16.02","high":"16.60","low":"16.02","close":"16.08","average":"16.2666","totalVolume":"71,287","turnover":"1,159,781.87","trades":"205"},{"dateTime":"2025-06-23","bid":"16.12","ask":"16.28","open":"16.60","high":"16.62","low":"15.80","close":"16.20","average":"16.2276","totalVolume":"52,328","turnover":"849,175.99","trades":"206"},{"dateTime":"2025-06-19","bid":"16.70","ask":"16.82","open":"16.72","high":"17.08","low":"16.48","close":"16.58","average":"16.6525","totalVolume":"46,127","turnover":"768,254.6","trades":"165"},{"dateTime":"2025-06-18","bid":"16.76","ask":"16.98","open":"17.84","high":"17.84","low":"16.70","close":"16.90","average":"17.1263","totalVolume":"109,105","turnover":"1,868,303.91","trades":"373"},{"dateTime":"2025-06-17","bid":"17.86","ask":"18.08","open":"18.80","high":"18.94","low":"17.86","close":"17.90","average":"18.3315","totalVolume":"51,538","turnover":"944,831.28","trades":"237"},{"dateTime":"2025-06-16","bid":"18.56","ask":"18.64","open":"17.70","high":"18.86","low":"17.70","close":"18.60","average":"18.6411","totalVolume":"217,054","turnover":"4,045,963.81","trades":"404"},{"dateTime":"2025-06-13","bid":"17.40","ask":"17.98","open":"17.80","high":"18.34","low":"17.30","close":"17.52","average":"17.8559","totalVolume":"122,681","turnover":"2,189,873.04","trades":"331"},{"dateTime":"2025-06-12","bid":"17.72","ask":"17.80","open":"17.80","high":"18.48","low":"17.36","close":"17.70","average":"17.8471","totalVolume":"54,423","turnover":"971,312.07","trades":"262"},{"dateTime":"2025-06-11","bid":"17.68","ask":"17.80","open":"17.46","high":"17.92","low":"16.90","close":"17.76","average":"17.4798","totalVolume":"71,975","turnover":"1,258,404.63","trades":"301"},{"dateTime":"2025-06-10","bid":"17.46","ask":"17.68","open":"18.50","high":"18.98","low":"17.32","close":"17.46","average":"18.3657","totalVolume":"236,739","turnover":"4,349,857.7","trades":"726"},{"dateTime":"2025-06-09","bid":"18.10","ask":"18.26","open":"18.00","high":"18.88","low":"17.34","close":"18.14","average":"18.1622","totalVolume":"574,398","turnover":"10,428,221.6","trades":"1,462"},{"dateTime":"2025-06-05","bid":"15.46","ask":"15.78","open":"16.02","high":"16.38","low":"14.98","close":"15.68","average":"15.8209","totalVolume":"92,813","turnover":"1,468,698.31","trades":"244"},{"dateTime":"2025-06-04","bid":"15.94","ask":"16.02","open":"15.28","high":"16.44","low":"15.00","close":"16.10","average":"15.6232","totalVolume":"199,895","turnover":"3,122,614.6","trades":"451"},{"dateTime":"2025-06-03","bid":"14.92","ask":"15.00","open":"14.92","high":"15.30","low":"14.68","close":"15.00","average":"15.0347","totalVolume":"64,921","turnover":"976,066.05","trades":"155"},{"dateTime":"2025-06-02","bid":"14.76","ask":"14.96","open":"15.08","high":"15.18","low":"14.28","close":"14.94","average":"14.7743","totalVolume":"70,360","turnover":"1,039,521.3","trades":"247"},{"dateTime":"2025-05-30","bid":"15.02","ask":"15.26","open":"14.70","high":"15.48","low":"14.52","close":"15.12","average":"15.0384","totalVolume":"145,992","turnover":"2,195,084.39","trades":"427"},{"dateTime":"2025-05-28","bid":"14.50","ask":"14.68","open":"14.52","high":"15.06","low":"14.10","close":"14.56","average":"14.6572","totalVolume":"139,077","turnover":"2,038,464.46","trades":"242"},{"dateTime":"2025-05-27","bid":"14.40","ask":"14.52","open":"14.82","high":"15.24","low":"14.32","close":"14.34","average":"14.8179","totalVolume":"217,294","turnover":"3,219,456.08","trades":"476"},{"dateTime":"2025-05-26","bid":"14.94","ask":"14.98","open":"15.70","high":"15.70","low":"14.52","close":"14.86","average":"14.8949","totalVolume":"450,257","turnover":"6,708,350.9","trades":"1,041"},{"dateTime":"2025-05-23","bid":"15.70","ask":"15.74","open":"17.70","high":"17.70","low":"15.22","close":"15.74","average":"16.0737","totalVolume":"611,788","turnover":"9,834,125.28","trades":"1,650"},{"dateTime":"2025-05-22","bid":"16.90","ask":"17.00","open":"16.24","high":"18.48","low":"15.00","close":"17.00","average":"16.9727","totalVolume":"2,222,082","turnover":"37,724,335","trades":"4,833"},{"dateTime":"2025-05-21","bid":"10.44","ask":"10.88","open":"10.96","high":"10.96","low":"10.24","close":"10.70","average":"10.5796","totalVolume":"45,940","turnover":"485,856.52","trades":"143"},{"dateTime":"2025-05-20","bid":"10.44","ask":"10.52","open":"9.93","high":"10.76","low":"9.93","close":"10.56","average":"10.3071","totalVolume":"110,742","turnover":"1,141,511.78","trades":"319"},{"dateTime":"2025-05-19","bid":"9.86","ask":"9.92","open":"9.96","high":"10.20","low":"9.57","close":"9.92","average":"9.8019","totalVolume":"12,838","turnover":"125,832.37","trades":"78"},{"dateTime":"2025-05-16","bid":"9.96","ask":"10.04","open":"10.30","high":"10.34","low":"9.95","close":"9.96","average":"10.0194","totalVolume":"30,292","turnover":"303,542.8","trades":"53"},{"dateTime":"2025-05-15","bid":"10.10","ask":"10.16","open":"10.80","high":"10.80","low":"9.52","close":"10.20","average":"10.0878","totalVolume":"29,531","turnover":"297,903.04","trades":"88"},{"dateTime":"2025-05-14","bid":"9.91","ask":"10.00","open":"9.80","high":"10.26","low":"9.70","close":"10.00","average":"9.9396","totalVolume":"123,181","turnover":"1,224,454.37","trades":"156"},{"dateTime":"2025-05-13","bid":"9.70","ask":"9.84","open":"9.70","high":"10.06","low":"9.52","close":"9.80","average":"9.746","totalVolume":"146,692","turnover":"1,429,776.69","trades":"171"},{"dateTime":"2025-05-12","bid":"9.60","ask":"9.70","open":"9.80","high":"9.80","low":"9.50","close":"9.60","average":"9.7194","totalVolume":"23,638","turnover":"229,814.02","trades":"70"},{"dateTime":"2025-05-09","bid":"9.70","ask":"9.80","open":"9.69","high":"9.80","low":"9.50","close":"9.80","average":"9.7078","totalVolume":"24,495","turnover":"237,833.64","trades":"99"},{"dateTime":"2025-05-08","bid":"9.53","ask":"9.69","open":"9.66","high":"9.87","low":"9.40","close":"9.60","average":"9.6625","totalVolume":"40,468","turnover":"391,041.05","trades":"126"},{"dateTime":"2025-05-07","bid":"9.46","ask":"9.57","open":"9.90","high":"9.97","low":"9.31","close":"9.43","average":"9.6096","totalVolume":"63,960","turnover":"614,708.05","trades":"160"},{"dateTime":"2025-05-06","bid":"9.72","ask":"9.80","open":"10.22","high":"10.98","low":"9.60","close":"9.72","average":"10.1393","totalVolume":"315,050","turnover":"3,194,461.99","trades":"387"},{"dateTime":"2025-05-05","bid":"10.22","ask":"10.30","open":"10.50","high":"10.50","low":"10.18","close":"10.28","average":"10.2845","totalVolume":"38,633","turnover":"397,321.16","trades":"89"},{"dateTime":"2025-05-02","bid":"10.20","ask":"10.26","open":"10.10","high":"10.30","low":"9.98","close":"10.28","average":"10.2387","totalVolume":"180,273","turnover":"1,845,714.69","trades":"134"},{"dateTime":"2025-04-30","bid":"9.99","ask":"10.22","open":"10.54","high":"10.54","low":"9.95","close":"9.95","average":"10.1758","totalVolume":"34,939","turnover":"355,540.99","trades":"67"},{"dateTime":"2025-04-29","bid":"10.40","ask":"10.48","open":"10.50","high":"10.50","low":"10.24","close":"10.48","average":"10.3821","totalVolume":"32,667","turnover":"339,153.22","trades":"71"},{"dateTime":"2025-04-28","bid":"10.44","ask":"10.50","open":"10.98","high":"10.98","low":"10.40","close":"10.50","average":"10.581","totalVolume":"39,793","turnover":"421,083.42","trades":"104"},{"dateTime":"2025-04-25","bid":"10.28","ask":"10.40","open":"10.68","high":"10.68","low":"10.20","close":"10.40","average":"10.3934","totalVolume":"35,845","turnover":"372,548.86","trades":"128"},{"dateTime":"2025-04-24","bid":"10.44","ask":"10.50","open":"10.40","high":"10.86","low":"10.32","close":"10.42","average":"10.5394","totalVolume":"59,278","turnover":"624,788.08","trades":"118"},{"dateTime":"2025-04-23","bid":"10.84","ask":"10.94","open":"10.20","high":"10.98","low":"10.08","close":"10.90","average":"10.3758","totalVolume":"75,791","turnover":"786,403.03","trades":"127"},{"dateTime":"2025-04-22","bid":"10.00","ask":"10.14","open":"10.12","high":"10.30","low":"10.00","close":"10.16","average":"10.0953","totalVolume":"30,336","turnover":"306,251.74","trades":"72"},{"dateTime":"2025-04-17","bid":"10.10","ask":"10.20","open":"10.08","high":"10.32","low":"10.04","close":"10.18","average":"10.1631","totalVolume":"27,217","turnover":"276,609.32","trades":"54"},{"dateTime":"2025-04-16","bid":"10.00","ask":"10.10","open":"10.66","high":"10.66","low":"9.95","close":"10.10","average":"10.0649","totalVolume":"35,732","turnover":"359,636.65","trades":"108"},{"dateTime":"2025-04-15","bid":"10.12","ask":"10.18","open":"10.62","high":"10.62","low":"10.00","close":"10.20","average":"10.3026","totalVolume":"90,297","turnover":"930,335.34","trades":"217"},{"dateTime":"2025-04-14","bid":"10.62","ask":"10.70","open":"10.88","high":"11.16","low":"10.44","close":"10.70","average":"10.7491","totalVolume":"32,509","turnover":"349,535.63","trades":"139"},{"dateTime":"2025-04-11","bid":"10.84","ask":"11.00","open":"11.20","high":"11.20","low":"10.20","close":"11.00","average":"10.7473","totalVolume":"17,248","turnover":"185,381.09","trades":"79"},{"dateTime":"2025-04-10","bid":"10.90","ask":"11.20","open":"11.38","high":"11.66","low":"10.92","close":"11.18","average":"11.1498","totalVolume":"32,535","turnover":"363,981.28","trades":"71"},{"dateTime":"2025-04-09","bid":"10.70","ask":"10.88","open":"10.40","high":"11.50","low":"10.22","close":"10.82","average":"10.6015","totalVolume":"11,916","turnover":"126,313.66","trades":"50"},{"dateTime":"2025-04-08","bid":"10.68","ask":"11.02","open":"10.98","high":"11.08","low":"10.68","close":"11.02","average":"10.8964","totalVolume":"19,103","turnover":"208,154.08","trades":"56"},{"dateTime":"2025-04-07","bid":"10.70","ask":"10.98","open":"11.00","high":"11.00","low":"9.60","close":"10.68","average":"10.45","totalVolume":"67,312","turnover":"703,409.92","trades":"156"},{"dateTime":"2025-04-04","bid":"10.57","ask":"10.81","open":"11.70","high":"11.70","low":"10.328","close":"10.81","average":"10.8117","totalVolume":"57,511","turnover":"621,822.73","trades":"157"},{"dateTime":"2025-04-03","bid":"11.40","ask":"11.598","open":"11.828","high":"11.998","low":"11.336","close":"11.40","average":"11.6817","totalVolume":"11,142","turnover":"130,126.44","trades":"52"},{"dateTime":"2025-04-02","bid":"11.828","ask":"11.962","open":"11.686","high":"12.186","low":"11.514","close":"11.78","average":"11.7299","totalVolume":"26,421","turnover":"309,912.99","trades":"84"},{"dateTime":"2025-04-01","bid":"11.686","ask":"11.998","open":"11.502","high":"12.00","low":"11.502","close":"12.00","average":"11.8471","totalVolume":"12,574","turnover":"148,965.35","trades":"50"},{"dateTime":"2025-03-31","bid":"11.626","ask":"11.898","open":"11.90","high":"12.00","low":"11.462","close":"11.896","average":"11.6752","totalVolume":"36,597","turnover":"427,328.05","trades":"92"},{"dateTime":"2025-03-28","bid":"11.70","ask":"11.942","open":"11.80","high":"12.00","low":"11.638","close":"11.70","average":"11.8623","totalVolume":"21,540","turnover":"255,523.45","trades":"64"},{"dateTime":"2025-03-27","bid":"11.926","ask":"11.994","open":"12.002","high":"12.228","low":"11.702","close":"11.926","average":"11.8706","totalVolume":"29,155","turnover":"346,087.99","trades":"77"},{"dateTime":"2025-03-26","bid":"11.942","ask":"12.002","open":"12.032","high":"12.14","low":"11.57","close":"12.00","average":"11.8703","totalVolume":"26,825","turnover":"318,438","trades":"77"},{"dateTime":"2025-03-25","bid":"11.804","ask":"11.886","open":"12.00","high":"12.252","low":"11.604","close":"11.804","average":"11.8767","totalVolume":"31,035","turnover":"368,585.5","trades":"73"},{"dateTime":"2025-03-24","bid":"11.582","ask":"11.792","open":"13.448","high":"13.448","low":"11.35","close":"11.632","average":"11.973","totalVolume":"202,185","turnover":"2,420,704.74","trades":"119"},{"dateTime":"2025-03-21","bid":"12.154","ask":"12.394","open":"12.478","high":"12.664","low":"12.00","close":"12.394","average":"12.0999","totalVolume":"80,389","turnover":"972,731.7","trades":"45"},{"dateTime":"2025-03-20","bid":"12.352","ask":"12.476","open":"13.498","high":"13.498","low":"12.292","close":"12.476","average":"12.791","totalVolume":"15,678","turnover":"200,578.59","trades":"72"},{"dateTime":"2025-03-19","bid":"","ask":"","open":"13.00","high":"13.29","low":"12.30","close":"12.92","average":"12.6462","totalVolume":"61,056","turnover":"772,126.96","trades":"187"},{"dateTime":"2025-03-18","bid":"12.40","ask":"12.45","open":"11.842","high":"12.49","low":"11.50","close":"12.40","average":"11.8579","totalVolume":"62,254","turnover":"738,200.94","trades":"152"},{"dateTime":"2025-03-17","bid":"11.656","ask":"11.844","open":"11.50","high":"12.00","low":"11.41","close":"11.654","average":"11.7314","totalVolume":"42,172","turnover":"494,740.77","trades":"118"},{"dateTime":"2025-03-14","bid":"11.424","ask":"11.596","open":"11.548","high":"11.60","low":"10.804","close":"11.60","average":"11.2097","totalVolume":"98,288","turnover":"1,101,787.69","trades":"176"},{"dateTime":"2025-03-13","bid":"11.50","ask":"11.542","open":"11.91","high":"12.078","low":"11.368","close":"11.548","average":"11.5688","totalVolume":"77,535","turnover":"897,120.17","trades":"192"},{"dateTime":"2025-03-12","bid":"11.70","ask":"11.916","open":"12.25","high":"12.578","low":"11.60","close":"11.914","average":"11.8785","totalVolume":"78,618","turnover":"933,910.67","trades":"186"},{"dateTime":"2025-03-11","bid":"11.854","ask":"12.226","open":"12.70","high":"13.00","low":"11.756","close":"12.25","average":"12.0689","totalVolume":"142,949","turnover":"1,725,238.41","trades":"388"},{"dateTime":"2025-03-10","bid":"12.65","ask":"12.70","open":"13.688","high":"13.748","low":"12.65","close":"12.708","average":"13.0622","totalVolume":"63,130","turnover":"824,574.92","trades":"267"},{"dateTime":"2025-03-07","bid":"13.106","ask":"13.30","open":"13.898","high":"14.338","low":"13.106","close":"13.288","average":"13.6349","totalVolume":"73,330","turnover":"999,871.61","trades":"193"},{"dateTime":"2025-03-06","bid":"13.652","ask":"13.994","open":"14.00","high":"14.30","low":"13.60","close":"13.696","average":"13.9531","totalVolume":"31,867","turnover":"444,686.32","trades":"126"},{"dateTime":"2025-03-05","bid":"14.00","ask":"14.15","open":"14.698","high":"14.70","low":"14.136","close":"14.148","average":"14.5139","totalVolume":"34,961","turnover":"507,388.57","trades":"117"},{"dateTime":"2025-03-04","bid":"13.826","ask":"14.136","open":"14.10","high":"14.36","low":"13.60","close":"14.134","average":"13.897","totalVolume":"94,536","turnover":"1,313,805.29","trades":"188"},{"dateTime":"2025-03-03","bid":"14.102","ask":"14.252","open":"14.10","high":"15.00","low":"14.084","close":"14.084","average":"14.3278","totalVolume":"387,283","turnover":"5,539,714.2","trades":"191"},{"dateTime":"2025-02-28","bid":"14.554","ask":"14.898","open":"14.624","high":"14.966","low":"14.02","close":"14.58","average":"14.6363","totalVolume":"43,661","turnover":"639,035.69","trades":"103"},{"dateTime":"2025-02-27","bid":"14.624","ask":"15.048","open":"14.916","high":"15.356","low":"14.50","close":"15.024","average":"14.9737","totalVolume":"57,320","turnover":"858,276.5","trades":"135"},{"dateTime":"2025-02-26","bid":"14.916","ask":"15.098","open":"15.00","high":"15.28","low":"14.538","close":"15.098","average":"14.9985","totalVolume":"145,898","turnover":"2,188,256","trades":"222"},{"dateTime":"2025-02-25","bid":"14.95","ask":"15.00","open":"15.00","high":"15.002","low":"14.45","close":"15.00","average":"14.7554","totalVolume":"105,715","turnover":"1,559,950.66","trades":"339"},{"dateTime":"2025-02-24","bid":"14.802","ask":"15.16","open":"16.30","high":"16.30","low":"14.604","close":"15.298","average":"15.0532","totalVolume":"102,788","turnover":"1,547,426.52","trades":"296"},{"dateTime":"2025-02-21","bid":"15.482","ask":"15.996","open":"15.90","high":"16.002","low":"15.21","close":"15.996","average":"15.6494","totalVolume":"112,648","turnover":"1,763,003.55","trades":"286"},{"dateTime":"2025-02-20","bid":"15.76","ask":"15.898","open":"16.562","high":"17.042","low":"15.372","close":"15.70","average":"15.8691","totalVolume":"352,988","turnover":"5,599,710.05","trades":"790"},{"dateTime":"2025-02-19","bid":"16.85","ask":"17.078","open":"17.422","high":"17.424","low":"16.85","close":"17.078","average":"17.1745","totalVolume":"41,419","turnover":"711,379.63","trades":"114"},{"dateTime":"2025-02-18","bid":"17.298","ask":"17.30","open":"17.64","high":"17.80","low":"17.20","close":"17.30","average":"17.457","totalVolume":"53,450","turnover":"933,077.05","trades":"129"},{"dateTime":"2025-02-17","bid":"17.60","ask":"17.64","open":"16.898","high":"17.70","low":"16.776","close":"17.60","average":"17.2267","totalVolume":"79,289","turnover":"1,365,879.24","trades":"215"},{"dateTime":"2025-02-14","bid":"16.656","ask":"16.776","open":"16.95","high":"16.95","low":"16.562","close":"16.898","average":"16.7084","totalVolume":"40,930","turnover":"683,887.24","trades":"161"},{"dateTime":"2025-02-13","bid":"16.95","ask":"16.998","open":"17.164","high":"17.216","low":"16.95","close":"16.95","average":"17.0339","totalVolume":"29,262","turnover":"498,467.58","trades":"111"},{"dateTime":"2025-02-12","bid":"17.154","ask":"17.292","open":"17.596","high":"17.60","low":"17.078","close":"17.15","average":"17.2651","totalVolume":"62,038","turnover":"1,071,112.12","trades":"203"},{"dateTime":"2025-02-11","bid":"17.40","ask":"17.474","open":"17.70","high":"17.70","low":"17.29","close":"17.698","average":"17.4991","totalVolume":"20,914","turnover":"365,995.64","trades":"165"},{"dateTime":"2025-02-10","bid":"17.70","ask":"17.702","open":"18.35","high":"18.35","low":"17.64","close":"17.70","average":"17.9308","totalVolume":"52,369","turnover":"939,017.67","trades":"206"},{"dateTime":"2025-02-07","bid":"18.002","ask":"18.086","open":"18.398","high":"18.40","low":"18.002","close":"18.354","average":"18.1517","totalVolume":"45,082","turnover":"818,293.37","trades":"192"},{"dateTime":"2025-02-06","bid":"18.01","ask":"18.848","open":"18.22","high":"18.40","low":"18.006","close":"18.344","average":"18.1153","totalVolume":"39,170","turnover":"709,574.13","trades":"182"},{"dateTime":"2025-02-05","bid":"18.31","ask":"18.392","open":"18.986","high":"19.082","low":"18.202","close":"18.31","average":"18.4378","totalVolume":"22,761","turnover":"419,703.89","trades":"189"},{"dateTime":"2025-02-04","bid":"18.90","ask":"18.978","open":"19.69","high":"19.69","low":"18.86","close":"18.986","average":"19.2927","totalVolume":"34,800","turnover":"671,267.17","trades":"128"},{"dateTime":"2025-02-03","bid":"19.45","ask":"19.652","open":"18.502","high":"19.698","low":"18.002","close":"19.698","average":"18.8089","totalVolume":"72,388","turnover":"1,361,522.1","trades":"226"},{"dateTime":"2025-01-31","bid":"18.408","ask":"18.984","open":"19.27","high":"19.27","low":"18.406","close":"18.984","average":"18.71","totalVolume":"28,068","turnover":"525,161.64","trades":"157"},{"dateTime":"2025-01-30","bid":"18.902","ask":"18.99","open":"18.434","high":"19.074","low":"18.012","close":"19.074","average":"18.553","totalVolume":"118,678","turnover":"2,200,734.96","trades":"254"},{"dateTime":"2025-01-29","bid":"18.002","ask":"18.432","open":"18.05","high":"18.99","low":"18.002","close":"18.43","average":"18.107","totalVolume":"46,701","turnover":"845,610.26","trades":"186"},{"dateTime":"2025-01-28","bid":"18.08","ask":"18.206","open":"18.38","high":"18.592","low":"18.078","close":"18.08","average":"18.177","totalVolume":"45,722","turnover":"831,120.43","trades":"193"},{"dateTime":"2025-01-27","bid":"18.202","ask":"18.38","open":"19.088","high":"19.088","low":"18.002","close":"18.204","average":"18.3588","totalVolume":"56,987","turnover":"1,046,185.59","trades":"251"},{"dateTime":"2025-01-24","bid":"18.682","ask":"19.098","open":"18.998","high":"19.156","low":"18.676","close":"18.682","average":"18.8936","totalVolume":"34,174","turnover":"645,669.81","trades":"152"},{"dateTime":"2025-01-23","bid":"18.832","ask":"18.998","open":"18.70","high":"19.362","low":"18.34","close":"19.00","average":"18.8174","totalVolume":"51,872","turnover":"976,095.96","trades":"147"},{"dateTime":"2025-01-22","bid":"18.552","ask":"18.758","open":"19.464","high":"19.488","low":"18.502","close":"18.54","average":"18.7799","totalVolume":"57,614","turnover":"1,081,983.37","trades":"177"},{"dateTime":"2025-01-21","bid":"19.304","ask":"19.464","open":"18.752","high":"19.60","low":"18.70","close":"19.464","average":"19.2931","totalVolume":"30,061","turnover":"579,970.83","trades":"121"},{"dateTime":"2025-01-20","bid":"18.752","ask":"18.978","open":"18.74","high":"19.002","low":"18.70","close":"18.754","average":"18.8586","totalVolume":"14,512","turnover":"273,676.58","trades":"69"},{"dateTime":"2025-01-17","bid":"18.704","ask":"18.846","open":"19.00","high":"19.318","low":"18.50","close":"18.70","average":"18.8305","totalVolume":"54,107","turnover":"1,018,861.71","trades":"176"},{"dateTime":"2025-01-16","bid":"19.00","ask":"19.092","open":"19.004","high":"19.334","low":"18.806","close":"19.00","average":"19.0023","totalVolume":"92,788","turnover":"1,763,200.11","trades":"183"},{"dateTime":"2025-01-15","bid":"19.008","ask":"19.248","open":"19.398","high":"19.73","low":"19.002","close":"19.18","average":"19.2587","totalVolume":"68,283","turnover":"1,315,034.59","trades":"181"},{"dateTime":"2025-01-14","bid":"19.048","ask":"19.252","open":"19.736","high":"20.475","low":"19.002","close":"19.254","average":"19.2831","totalVolume":"45,882","turnover":"884,750.05","trades":"176"},{"dateTime":"2025-01-13","bid":"19.372","ask":"19.526","open":"20.48","high":"20.48","low":"19.352","close":"19.524","average":"19.7136","totalVolume":"34,509","turnover":"680,277.86","trades":"165"},{"dateTime":"2025-01-10","bid":"19.88","ask":"20.12","open":"21.05","high":"21.165","low":"19.498","close":"20.115","average":"20.0415","totalVolume":"316,118","turnover":"6,341,095.01","trades":"418"},{"dateTime":"2025-01-09","bid":"21.165","ask":"21.19","open":"21.10","high":"21.40","low":"20.55","close":"21.165","average":"21.2083","totalVolume":"28,904","turnover":"613,010.26","trades":"133"},{"dateTime":"2025-01-08","bid":"21.10","ask":"21.18","open":"21.945","high":"22.035","low":"20.305","close":"21.165","average":"21.0149","totalVolume":"163,233","turnover":"3,430,486.43","trades":"324"},{"dateTime":"2025-01-07","bid":"21.80","ask":"21.94","open":"23.00","high":"23.495","low":"21.50","close":"21.76","average":"22.5774","totalVolume":"71,333","turnover":"1,610,509.87","trades":"253"},{"dateTime":"2025-01-03","bid":"23.00","ask":"23.19","open":"22.21","high":"23.26","low":"22.21","close":"22.90","average":"22.6585","totalVolume":"76,165","turnover":"1,725,643.68","trades":"288"},{"dateTime":"2025-01-02","bid":"22.16","ask":"22.20","open":"21.32","high":"22.615","low":"21.32","close":"22.20","average":"22.1085","totalVolume":"63,391","turnover":"1,401,465.68","trades":"272"},{"dateTime":"2024-12-30","bid":"21.01","ask":"21.385","open":"20.775","high":"21.65","low":"20.60","close":"21.38","average":"21.184","totalVolume":"155,488","turnover":"3,293,935.72","trades":"456"},{"dateTime":"2024-12-27","bid":"20.31","ask":"20.50","open":"19.998","high":"20.89","low":"19.402","close":"20.50","average":"20.4753","totalVolume":"71,842","turnover":"1,471,074.56","trades":"363"},{"dateTime":"2024-12-23","bid":"20.06","ask":"20.38","open":"20.295","high":"20.93","low":"20.00","close":"20.05","average":"20.4642","totalVolume":"54,907","turnover":"1,123,630.49","trades":"193"},{"dateTime":"2024-12-20","bid":"20.205","ask":"20.38","open":"19.682","high":"20.78","low":"19.292","close":"20.295","average":"19.7428","totalVolume":"75,418","turnover":"1,488,394.66","trades":"294"},{"dateTime":"2024-12-19","bid":"19.532","ask":"19.682","open":"19.89","high":"20.03","low":"19.50","close":"19.658","average":"19.7413","totalVolume":"96,891","turnover":"1,910,685.19","trades":"315"},{"dateTime":"2024-12-18","bid":"20.25","ask":"20.335","open":"20.815","high":"21.475","low":"20.05","close":"20.20","average":"20.5973","totalVolume":"224,013","turnover":"4,612,629.76","trades":"554"},{"dateTime":"2024-12-17","bid":"21.485","ask":"21.695","open":"22.005","high":"22.005","low":"20.835","close":"21.475","average":"21.3592","totalVolume":"134,960","turnover":"2,882,530.5","trades":"412"},{"dateTime":"2024-12-16","bid":"22.27","ask":"22.435","open":"23.85","high":"23.85","low":"21.995","close":"22.185","average":"22.7376","totalVolume":"69,147","turnover":"1,572,197.75","trades":"228"},{"dateTime":"2024-12-13","bid":"23.60","ask":"23.86","open":"24.65","high":"24.65","low":"23.60","close":"23.60","average":"24.1378","totalVolume":"113,434","turnover":"2,733,316.64","trades":"265"},{"dateTime":"2024-12-12","bid":"24.50","ask":"24.53","open":"23.825","high":"24.70","low":"23.30","close":"24.53","average":"23.9722","totalVolume":"74,852","turnover":"1,794,352.4","trades":"337"},{"dateTime":"2024-12-11","bid":"23.25","ask":"23.30","open":"21.425","high":"23.48","low":"21.01","close":"23.34","average":"22.3989","totalVolume":"150,467","turnover":"3,370,275.69","trades":"477"},{"dateTime":"2024-12-10","bid":"21.32","ask":"21.45","open":"19.50","high":"21.485","low":"19.48","close":"21.385","average":"20.3844","totalVolume":"282,694","turnover":"5,732,978.04","trades":"690"},{"dateTime":"2024-12-09","bid":"19.452","ask":"19.50","open":"19.664","high":"19.758","low":"19.302","close":"19.50","average":"19.5638","totalVolume":"34,758","turnover":"680,115.68","trades":"121"},{"dateTime":"2024-12-06","bid":"19.546","ask":"19.64","open":"19.506","high":"20.095","low":"19.506","close":"19.638","average":"19.6122","totalVolume":"68,794","turnover":"1,349,682.37","trades":"184"},{"dateTime":"2024-12-05","bid":"19.506","ask":"19.878","open":"20.075","high":"20.295","low":"19.50","close":"19.502","average":"19.7578","totalVolume":"109,219","turnover":"2,159,230.31","trades":"255"},{"dateTime":"2024-12-04","bid":"19.666","ask":"19.778","open":"19.004","high":"20.00","low":"18.812","close":"19.82","average":"19.4397","totalVolume":"264,785","turnover":"5,157,475.95","trades":"621"},{"dateTime":"2024-12-03","bid":"19.004","ask":"19.108","open":"19.60","high":"19.602","low":"18.99","close":"19.002","average":"19.1768","totalVolume":"72,362","turnover":"1,387,669.03","trades":"303"},{"dateTime":"2024-12-02","bid":"19.60","ask":"19.78","open":"19.468","high":"20.05","low":"19.304","close":"19.758","average":"19.7789","totalVolume":"50,280","turnover":"994,480.43","trades":"151"},{"dateTime":"2024-11-29","bid":"19.468","ask":"19.988","open":"19.50","high":"21.00","low":"19.004","close":"20.00","average":"19.9041","totalVolume":"294,409","turnover":"5,860,797.26","trades":"349"},{"dateTime":"2024-11-28","bid":"19.596","ask":"19.698","open":"19.66","high":"19.756","low":"19.302","close":"19.596","average":"19.5837","totalVolume":"79,617","turnover":"1,559,187.91","trades":"291"},{"dateTime":"2024-11-27","bid":"19.66","ask":"19.862","open":"19.60","high":"20.10","low":"19.356","close":"19.75","average":"19.7973","totalVolume":"24,344","turnover":"482,216.98","trades":"121"},{"dateTime":"2024-11-26","bid":"19.70","ask":"19.978","open":"19.80","high":"20.27","low":"19.116","close":"19.898","average":"19.7503","totalVolume":"51,435","turnover":"1,017,229.67","trades":"192"},{"dateTime":"2024-11-25","bid":"20.115","ask":"20.20","open":"20.10","high":"20.515","low":"19.798","close":"19.866","average":"20.2813","totalVolume":"115,424","turnover":"2,338,916.33","trades":"256"},{"dateTime":"2024-11-22","bid":"20.02","ask":"20.14","open":"19.90","high":"20.31","low":"19.85","close":"20.01","average":"20.053","totalVolume":"35,545","turnover":"712,785.36","trades":"249"},{"dateTime":"2024-11-21","bid":"19.654","ask":"19.828","open":"20.30","high":"20.485","low":"19.304","close":"19.656","average":"19.9296","totalVolume":"43,595","turnover":"868,830.87","trades":"257"},{"dateTime":"2024-11-20","bid":"20.145","ask":"20.215","open":"19.802","high":"20.50","low":"19.802","close":"20.145","average":"20.2325","totalVolume":"87,750","turnover":"1,775,313.88","trades":"270"},{"dateTime":"2024-11-19","bid":"19.33","ask":"19.622","open":"20.25","high":"20.48","low":"19.214","close":"19.364","average":"19.8762","totalVolume":"61,038","turnover":"1,213,200.83","trades":"395"},{"dateTime":"2024-11-18","bid":"20.205","ask":"20.26","open":"20.70","high":"20.80","low":"20.145","close":"20.225","average":"20.4878","totalVolume":"27,086","turnover":"554,932.59","trades":"168"},{"dateTime":"2024-11-15","bid":"20.50","ask":"20.765","open":"20.99","high":"21.00","low":"20.50","close":"20.765","average":"20.7305","totalVolume":"153,712","turnover":"3,187,585.79","trades":"147"},{"dateTime":"2024-11-14","bid":"21.03","ask":"21.335","open":"22.60","high":"23.32","low":"20.72","close":"21.00","average":"21.313","totalVolume":"104,083","turnover":"2,218,274.45","trades":"449"},{"dateTime":"2024-11-13","bid":"22.35","ask":"22.595","open":"21.715","high":"23.465","low":"21.21","close":"22.40","average":"21.7725","totalVolume":"88,328","turnover":"1,923,120.84","trades":"127"},{"dateTime":"2024-11-12","bid":"21.52","ask":"21.71","open":"23.00","high":"23.00","low":"21.50","close":"21.705","average":"21.7843","totalVolume":"69,894","turnover":"1,518,650.21","trades":"247"},{"dateTime":"2024-11-11","bid":"23.00","ask":"23.30","open":"23.005","high":"23.005","low":"22.60","close":"22.795","average":"22.7792","totalVolume":"37,399","turnover":"851,926.26","trades":"282"},{"dateTime":"2024-11-08","bid":"23.00","ask":"23.775","open":"23.20","high":"24.625","low":"22.69","close":"23.005","average":"23.558","totalVolume":"59,376","turnover":"1,398,777.71","trades":"147"},{"dateTime":"2024-11-07","bid":"22.725","ask":"23.195","open":"22.975","high":"23.195","low":"22.22","close":"23.195","average":"22.6823","totalVolume":"33,394","turnover":"757,743.86","trades":"152"},{"dateTime":"2024-11-06","bid":"22.655","ask":"22.985","open":"23.585","high":"23.585","low":"22.60","close":"22.98","average":"22.8603","totalVolume":"60,654","turnover":"1,386,570.31","trades":"146"},{"dateTime":"2024-11-05","bid":"23.365","ask":"23.595","open":"24.13","high":"24.13","low":"23.23","close":"23.595","average":"23.7773","totalVolume":"41,568","turnover":"989,618.27","trades":"126"},{"dateTime":"2024-11-04","bid":"24.12","ask":"24.41","open":"24.605","high":"25.155","low":"24.025","close":"24.13","average":"24.3776","totalVolume":"64,439","turnover":"1,571,032.16","trades":"199"},{"dateTime":"2024-11-01","bid":"24.615","ask":"25.28","open":"25.625","high":"25.72","low":"24.61","close":"24.61","average":"24.8627","totalVolume":"51,645","turnover":"1,284,455.38","trades":"303"},{"dateTime":"2024-10-31","bid":"25.85","ask":"25.99","open":"25.82","high":"26.40","low":"25.625","close":"25.755","average":"26.0727","totalVolume":"39,436","turnover":"1,028,113.46","trades":"237"},{"dateTime":"2024-10-30","bid":"25.82","ask":"25.92","open":"26.45","high":"26.45","low":"25.495","close":"25.82","average":"25.6977","totalVolume":"15,391","turnover":"395,513.19","trades":"83"},{"dateTime":"2024-10-29","bid":"25.83","ask":"25.995","open":"25.53","high":"27.05","low":"25.53","close":"25.83","average":"25.8963","totalVolume":"12,110","turnover":"313,604.44","trades":"73"},{"dateTime":"2024-10-28","bid":"25.53","ask":"25.56","open":"25.53","high":"26.28","low":"25.53","close":"25.53","average":"25.726","totalVolume":"29,767","turnover":"766,421.36","trades":"121"},{"dateTime":"2024-10-25","bid":"25.975","ask":"26.22","open":"26.00","high":"26.495","low":"25.71","close":"25.975","average":"26.0191","totalVolume":"11,311","turnover":"294,428.91","trades":"84"},{"dateTime":"2024-10-24","bid":"25.855","ask":"26.00","open":"25.91","high":"27.405","low":"25.64","close":"26.00","average":"25.9392","totalVolume":"90,470","turnover":"2,349,322.58","trades":"144"},{"dateTime":"2024-10-23","bid":"25.905","ask":"26.225","open":"26.655","high":"27.00","low":"25.90","close":"25.905","average":"26.2167","totalVolume":"35,966","turnover":"942,909.59","trades":"229"},{"dateTime":"2024-10-22","bid":"26.70","ask":"26.79","open":"27.195","high":"27.195","low":"26.65","close":"26.65","average":"26.8901","totalVolume":"14,539","turnover":"390,955.92","trades":"92"},{"dateTime":"2024-10-21","bid":"27.01","ask":"27.195","open":"27.295","high":"27.30","low":"26.875","close":"27.195","average":"27.0608","totalVolume":"43,661","turnover":"1,181,500.37","trades":"88"},{"dateTime":"2024-10-18","bid":"27.30","ask":"27.365","open":"27.105","high":"27.635","low":"27.105","close":"27.30","average":"27.2573","totalVolume":"20,591","turnover":"561,255.02","trades":"48"},{"dateTime":"2024-10-17","bid":"27.10","ask":"27.125","open":"27.485","high":"27.485","low":"27.10","close":"27.125","average":"27.1978","totalVolume":"13,441","turnover":"365,565.24","trades":"70"},{"dateTime":"2024-10-16","bid":"27.50","ask":"27.545","open":"27.78","high":"27.78","low":"27.30","close":"27.485","average":"27.462","totalVolume":"16,717","turnover":"459,210.81","trades":"47"},{"dateTime":"2024-10-15","bid":"27.315","ask":"27.79","open":"28.00","high":"28.34","low":"27.00","close":"27.78","average":"27.3331","totalVolume":"14,758","turnover":"403,381.92","trades":"74"},{"dateTime":"2024-10-14","bid":"28.00","ask":"28.37","open":"28.485","high":"28.99","low":"28.00","close":"28.00","average":"28.2186","totalVolume":"19,544","turnover":"552,321.41","trades":"76"},{"dateTime":"2024-10-11","bid":"28.49","ask":"28.505","open":"28.80","high":"29.50","low":"28.24","close":"28.475","average":"28.4957","totalVolume":"19,671","turnover":"560,960.12","trades":"99"},{"dateTime":"2024-10-10","bid":"28.80","ask":"29.00","open":"28.165","high":"29.20","low":"28.165","close":"28.80","average":"28.8152","totalVolume":"26,180","turnover":"754,382.38","trades":"86"},{"dateTime":"2024-10-09","bid":"28.28","ask":"28.875","open":"29.40","high":"29.40","low":"28.155","close":"28.155","average":"28.8049","totalVolume":"15,703","turnover":"452,324.1","trades":"67"},{"dateTime":"2024-10-08","bid":"28.405","ask":"28.79","open":"28.705","high":"28.995","low":"28.405","close":"28.405","average":"28.7474","totalVolume":"11,212","turnover":"322,315.84","trades":"46"},{"dateTime":"2024-10-07","bid":"28.71","ask":"28.895","open":"29.215","high":"29.50","low":"28.01","close":"28.705","average":"28.8972","totalVolume":"59,945","turnover":"1,728,817.85","trades":"99"},{"dateTime":"2024-10-04","bid":"29.00","ask":"29.365","open":"28.40","high":"29.50","low":"28.005","close":"29.215","average":"29.0254","totalVolume":"94,296","turnover":"2,736,546.2","trades":"415"},{"dateTime":"2024-10-03","bid":"28.20","ask":"28.355","open":"27.89","high":"28.615","low":"27.81","close":"28.40","average":"28.2362","totalVolume":"24,942","turnover":"704,549.98","trades":"100"},{"dateTime":"2024-10-02","bid":"27.705","ask":"27.89","open":"27.96","high":"28.465","low":"27.205","close":"27.89","average":"27.7778","totalVolume":"8,183","turnover":"227,306.07","trades":"63"},{"dateTime":"2024-10-01","bid":"28.03","ask":"28.255","open":"28.10","high":"28.68","low":"27.96","close":"27.96","average":"28.0638","totalVolume":"31,395","turnover":"881,063.24","trades":"75"},{"dateTime":"2024-09-30","bid":"28.03","ask":"28.30","open":"28.00","high":"28.50","low":"27.51","close":"28.03","average":"28.1065","totalVolume":"30,907","turnover":"868,661.71","trades":"74"},{"dateTime":"2024-09-27","bid":"27.81","ask":"28.00","open":"28.41","high":"28.415","low":"27.70","close":"28.00","average":"28.158","totalVolume":"4,580","turnover":"128,963.84","trades":"50"},{"dateTime":"2024-09-26","bid":"28.04","ask":"28.375","open":"28.20","high":"28.50","low":"28.00","close":"28.00","average":"28.3256","totalVolume":"30,579","turnover":"865,871.46","trades":"106"},{"dateTime":"2024-09-25","bid":"27.67","ask":"28.005","open":"28.005","high":"28.495","low":"27.67","close":"28.005","average":"28.1671","totalVolume":"39,331","turnover":"1,107,885.67","trades":"101"},{"dateTime":"2024-09-24","bid":"28.00","ask":"28.36","open":"28.01","high":"28.58","low":"27.50","close":"28.005","average":"27.9715","totalVolume":"24,391","turnover":"682,443.1","trades":"125"},{"dateTime":"2024-09-23","bid":"28.00","ask":"28.815","open":"28.60","high":"28.985","low":"28.00","close":"28.00","average":"28.6796","totalVolume":"127,308","turnover":"3,648,380.14","trades":"320"},{"dateTime":"2024-09-20","bid":"27.905","ask":"28.395","open":"28.275","high":"28.395","low":"27.905","close":"27.905","average":"28.1429","totalVolume":"5,997","turnover":"168,773.1","trades":"54"},{"dateTime":"2024-09-19","bid":"28.10","ask":"28.27","open":"27.945","high":"28.395","low":"27.945","close":"28.105","average":"28.1521","totalVolume":"15,497","turnover":"436,433.19","trades":"118"},{"dateTime":"2024-09-18","bid":"28.005","ask":"28.19","open":"28.495","high":"28.495","low":"27.845","close":"28.005","average":"28.0425","totalVolume":"11,543","turnover":"323,719.84","trades":"104"},{"dateTime":"2024-09-17","bid":"28.015","ask":"28.50","open":"28.485","high":"28.53","low":"28.005","close":"28.495","average":"28.4236","totalVolume":"17,659","turnover":"501,932.5","trades":"79"},{"dateTime":"2024-09-16","bid":"28.00","ask":"28.225","open":"27.805","high":"28.355","low":"27.615","close":"28.00","average":"28.2158","totalVolume":"25,736","turnover":"726,160.75","trades":"118"},{"dateTime":"2024-09-13","bid":"27.905","ask":"28.10","open":"27.73","high":"28.235","low":"27.285","close":"27.805","average":"27.8223","totalVolume":"20,391","turnover":"567,322.39","trades":"127"},{"dateTime":"2024-09-12","bid":"27.435","ask":"27.90","open":"27.02","high":"28.485","low":"27.01","close":"27.73","average":"27.678","totalVolume":"15,275","turnover":"422,782.22","trades":"107"},{"dateTime":"2024-09-11","bid":"27.015","ask":"27.195","open":"27.805","high":"27.805","low":"27.00","close":"27.02","average":"27.3292","totalVolume":"19,995","turnover":"546,447.92","trades":"193"},{"dateTime":"2024-09-10","bid":"27.805","ask":"27.915","open":"28.50","high":"28.745","low":"27.805","close":"27.87","average":"28.1635","totalVolume":"57,804","turnover":"1,627,962.44","trades":"247"},{"dateTime":"2024-09-09","bid":"28.465","ask":"28.55","open":"28.705","high":"29.395","low":"28.385","close":"28.50","average":"28.6731","totalVolume":"24,103","turnover":"691,078.67","trades":"94"},{"dateTime":"2024-09-06","bid":"28.60","ask":"28.855","open":"28.955","high":"29.295","low":"28.405","close":"28.705","average":"28.864","totalVolume":"58,443","turnover":"1,686,903.14","trades":"133"},{"dateTime":"2024-09-05","bid":"29.00","ask":"29.265","open":"28.725","high":"30.43","low":"28.50","close":"29.00","average":"28.9228","totalVolume":"38,634","turnover":"1,117,403.07","trades":"147"},{"dateTime":"2024-09-04","bid":"28.47","ask":"28.72","open":"29.195","high":"29.195","low":"28.40","close":"28.725","average":"28.757","totalVolume":"38,745","turnover":"1,114,191.22","trades":"231"},{"dateTime":"2024-09-03","bid":"29.235","ask":"29.695","open":"30.835","high":"30.835","low":"29.205","close":"29.695","average":"29.7219","totalVolume":"31,165","turnover":"926,286.26","trades":"204"},{"dateTime":"2024-09-02","bid":"30.12","ask":"30.89","open":"30.45","high":"31.30","low":"29.85","close":"30.885","average":"30.2745","totalVolume":"39,083","turnover":"1,183,217.83","trades":"155"},{"dateTime":"2024-08-30","bid":"30.22","ask":"30.77","open":"30.995","high":"30.995","low":"30.10","close":"30.50","average":"30.5226","totalVolume":"16,650","turnover":"508,200.8","trades":"90"},{"dateTime":"2024-08-29","bid":"30.515","ask":"30.825","open":"30.80","high":"30.86","low":"30.20","close":"30.805","average":"30.6129","totalVolume":"30,059","turnover":"920,447.66","trades":"117"},{"dateTime":"2024-08-28","bid":"30.805","ask":"31.05","open":"30.56","high":"31.245","low":"30.50","close":"30.805","average":"30.8708","totalVolume":"30,543","turnover":"943,165.52","trades":"122"},{"dateTime":"2024-08-27","bid":"30.565","ask":"30.815","open":"31.00","high":"31.295","low":"30.35","close":"30.56","average":"30.8011","totalVolume":"11,659","turnover":"359,088.01","trades":"61"},{"dateTime":"2024-08-26","bid":"30.595","ask":"31.295","open":"30.815","high":"31.41","low":"30.10","close":"30.60","average":"30.9406","totalVolume":"65,819","turnover":"2,036,470.15","trades":"187"},{"dateTime":"2024-08-23","bid":"30.43","ask":"30.895","open":"30.15","high":"31.195","low":"29.80","close":"30.815","average":"30.2308","totalVolume":"35,369","turnover":"1,074,293.55","trades":"106"},{"dateTime":"2024-08-22","bid":"30.275","ask":"30.49","open":"30.595","high":"30.595","low":"30.00","close":"30.275","average":"30.2749","totalVolume":"42,518","turnover":"1,287,210.8","trades":"157"},{"dateTime":"2024-08-21","bid":"30.60","ask":"30.70","open":"30.50","high":"31.295","low":"30.195","close":"30.60","average":"30.6353","totalVolume":"51,238","turnover":"1,569,693.87","trades":"140"},{"dateTime":"2024-08-20","bid":"30.305","ask":"30.635","open":"31.00","high":"31.005","low":"30.125","close":"30.50","average":"30.6789","totalVolume":"17,245","turnover":"529,057.05","trades":"155"},{"dateTime":"2024-08-19","bid":"31.015","ask":"31.23","open":"31.41","high":"31.545","low":"31.00","close":"31.005","average":"31.1539","totalVolume":"46,856","turnover":"1,460,737.05","trades":"120"},{"dateTime":"2024-08-16","bid":"31.325","ask":"31.50","open":"31.345","high":"31.90","low":"30.20","close":"31.565","average":"31.2389","totalVolume":"44,740","turnover":"1,397,627.88","trades":"163"},{"dateTime":"2024-08-15","bid":"30.905","ask":"31.35","open":"31.315","high":"31.46","low":"30.55","close":"31.345","average":"31.0595","totalVolume":"8,744","turnover":"271,613.26","trades":"81"},{"dateTime":"2024-08-14","bid":"30.615","ask":"30.90","open":"30.945","high":"31.895","low":"30.49","close":"30.895","average":"30.9265","totalVolume":"27,081","turnover":"838,600.85","trades":"145"},{"dateTime":"2024-08-13","bid":"31.00","ask":"31.17","open":"31.90","high":"31.90","low":"30.945","close":"30.945","average":"31.2093","totalVolume":"43,441","turnover":"1,354,752.6","trades":"225"},{"dateTime":"2024-08-12","bid":"31.605","ask":"31.995","open":"33.40","high":"33.615","low":"31.80","close":"31.915","average":"32.2724","totalVolume":"87,896","turnover":"2,842,241.52","trades":"287"},{"dateTime":"2024-08-09","bid":"32.955","ask":"33.00","open":"31.72","high":"33.155","low":"31.10","close":"32.915","average":"32.122","totalVolume":"366,917","turnover":"11,799,055.84","trades":"868"},{"dateTime":"2024-08-08","bid":"30.00","ask":"30.14","open":"30.295","high":"30.30","low":"29.50","close":"30.15","average":"29.8596","totalVolume":"79,469","turnover":"2,372,895.17","trades":"378"},{"dateTime":"2024-08-07","bid":"30.305","ask":"30.37","open":"30.00","high":"31.495","low":"30.00","close":"30.37","average":"30.6276","totalVolume":"21,511","turnover":"658,557.25","trades":"149"},{"dateTime":"2024-08-06","bid":"29.995","ask":"30.29","open":"29.825","high":"31.00","low":"29.825","close":"30.00","average":"30.2072","totalVolume":"40,277","turnover":"1,217,375.24","trades":"259"},{"dateTime":"2024-08-05","bid":"29.97","ask":"29.995","open":"29.84","high":"30.985","low":"28.96","close":"29.73","average":"29.7328","totalVolume":"158,065","turnover":"4,699,718.79","trades":"519"},{"dateTime":"2024-08-02","bid":"31.445","ask":"31.815","open":"34.50","high":"34.50","low":"31.205","close":"31.485","average":"32.039","totalVolume":"241,601","turnover":"7,741,909.78","trades":"660"},{"dateTime":"2024-08-01","bid":"33.90","ask":"34.20","open":"34.30","high":"35.20","low":"33.70","close":"34.00","average":"34.1075","totalVolume":"100,477","turnover":"3,430,986.4","trades":"327"},{"dateTime":"2024-07-31","bid":"34.20","ask":"34.60","open":"32.10","high":"35.30","low":"32.10","close":"34.20","average":"34.1191","totalVolume":"385,784","turnover":"13,161,404.65","trades":"1,016"},{"dateTime":"2024-07-30","bid":"31.70","ask":"32.00","open":"31.70","high":"32.90","low":"31.70","close":"31.80","average":"31.8528","totalVolume":"32,789","turnover":"1,044,423","trades":"118"},{"dateTime":"2024-07-29","bid":"31.60","ask":"31.80","open":"31.60","high":"32.20","low":"31.00","close":"31.70","average":"31.5895","totalVolume":"96,756","turnover":"3,056,533.95","trades":"284"},{"dateTime":"2024-07-26","bid":"31.40","ask":"31.50","open":"31.30","high":"31.80","low":"31.30","close":"31.60","average":"31.6097","totalVolume":"17,712","turnover":"559,835.1","trades":"121"},{"dateTime":"2024-07-25","bid":"31.20","ask":"31.40","open":"31.50","high":"32.00","low":"31.10","close":"31.30","average":"31.38","totalVolume":"39,792","turnover":"1,248,671.89","trades":"189"},{"dateTime":"2024-07-24","bid":"31.40","ask":"31.60","open":"31.70","high":"31.90","low":"31.50","close":"31.50","average":"31.606","totalVolume":"43,019","turnover":"1,360,126.2","trades":"135"},{"dateTime":"2024-07-23","bid":"31.70","ask":"31.90","open":"31.60","high":"32.40","low":"30.70","close":"31.70","average":"31.3932","totalVolume":"135,227","turnover":"4,247,604","trades":"312"},{"dateTime":"2024-07-22","bid":"31.60","ask":"31.80","open":"32.80","high":"32.80","low":"31.60","close":"31.60","average":"31.925","totalVolume":"98,883","turnover":"3,156,875.7","trades":"303"},{"dateTime":"2024-07-19","bid":"32.70","ask":"32.90","open":"33.00","high":"33.00","low":"32.50","close":"32.80","average":"32.7236","totalVolume":"157,509","turnover":"5,154,269.09","trades":"209"},{"dateTime":"2024-07-18","bid":"33.00","ask":"33.10","open":"33.40","high":"33.60","low":"32.90","close":"33.00","average":"33.2271","totalVolume":"204,731","turnover":"6,802,616.7","trades":"260"},{"dateTime":"2024-07-17","bid":"33.50","ask":"33.60","open":"33.70","high":"33.70","low":"33.20","close":"33.50","average":"33.4166","totalVolume":"200,918","turnover":"6,713,962.4","trades":"255"},{"dateTime":"2024-07-16","bid":"33.30","ask":"33.50","open":"33.90","high":"33.90","low":"33.30","close":"33.70","average":"33.5539","totalVolume":"200,894","turnover":"6,740,774.5","trades":"270"},{"dateTime":"2024-07-15","bid":"33.80","ask":"33.90","open":"34.00","high":"34.40","low":"33.50","close":"33.80","average":"33.965","totalVolume":"325,240","turnover":"11,046,722.2","trades":"527"},{"dateTime":"2024-07-12","bid":"33.90","ask":"34.10","open":"34.20","high":"34.30","low":"33.40","close":"34.20","average":"33.7686","totalVolume":"176,145","turnover":"5,951,774.85","trades":"402"},{"dateTime":"2024-07-11","bid":"34.30","ask":"34.40","open":"34.90","high":"34.90","low":"34.00","close":"34.20","average":"34.3528","totalVolume":"200,463","turnover":"6,886,468.1","trades":"329"},{"dateTime":"2024-07-10","bid":"34.80","ask":"35.00","open":"35.00","high":"35.00","low":"34.10","close":"35.00","average":"34.6968","totalVolume":"262,211","turnover":"9,097,836.05","trades":"328"},{"dateTime":"2024-07-09","bid":"34.60","ask":"34.90","open":"33.50","high":"34.90","low":"32.80","close":"34.90","average":"34.1542","totalVolume":"437,473","turnover":"14,942,955.15","trades":"740"},{"dateTime":"2024-07-08","bid":"33.10","ask":"33.40","open":"33.80","high":"33.90","low":"32.60","close":"33.50","average":"33.2886","totalVolume":"149,893","turnover":"4,989,733.8","trades":"310"},{"dateTime":"2024-07-05","bid":"33.50","ask":"33.60","open":"33.20","high":"33.60","low":"32.30","close":"33.60","average":"32.9914","totalVolume":"253,619","turnover":"8,367,251.7","trades":"547"},{"dateTime":"2024-07-04","bid":"33.00","ask":"33.10","open":"35.10","high":"35.30","low":"32.80","close":"33.00","average":"33.6443","totalVolume":"449,297","turnover":"15,115,103.4","trades":"822"},{"dateTime":"2024-07-03","bid":"34.70","ask":"34.80","open":"34.30","high":"35.40","low":"34.10","close":"35.00","average":"34.916","totalVolume":"394,410","turnover":"13,767,286.55","trades":"1,006"},{"dateTime":"2024-07-02","bid":"34.30","ask":"34.40","open":"31.50","high":"34.50","low":"31.20","close":"34.20","average":"33.1621","totalVolume":"765,746","turnover":"25,391,434.25","trades":"1,626"},{"dateTime":"2024-07-01","bid":"31.20","ask":"31.30","open":"31.90","high":"32.40","low":"30.60","close":"31.50","average":"31.4376","totalVolume":"399,415","turnover":"12,545,714.55","trades":"890"},{"dateTime":"2024-06-28","bid":"30.90","ask":"31.00","open":"30.70","high":"32.20","low":"30.70","close":"31.00","average":"31.4185","totalVolume":"476,774","turnover":"14,974,510.5","trades":"1,037"},{"dateTime":"2024-06-27","bid":"30.30","ask":"30.50","open":"30.10","high":"31.30","low":"30.10","close":"30.50","average":"30.7392","totalVolume":"339,065","turnover":"10,422,740.19","trades":"838"},{"dateTime":"2024-06-26","bid":"30.40","ask":"30.50","open":"32.90","high":"32.90","low":"30.10","close":"30.10","average":"30.984","totalVolume":"812,016","turnover":"25,160,476.9","trades":"1,342"},{"dateTime":"2024-06-25","bid":"32.30","ask":"32.40","open":"33.10","high":"33.60","low":"32.00","close":"32.60","average":"32.7625","totalVolume":"507,326","turnover":"16,621,254.25","trades":"741"},{"dateTime":"2024-06-24","bid":"32.69","ask":"32.695","open":"33.00","high":"33.775","low":"31.00","close":"33.10","average":"32.6026","totalVolume":"893,033","turnover":"29,117,673.56","trades":"2,355"},{"dateTime":"2024-06-20","bid":"32.72","ask":"32.80","open":"40.00","high":"40.00","low":"32.475","close":"32.605","average":"35.4377","totalVolume":"4,642,609","turnover":"164,512,030.81","trades":"8,435"}]}},"messages":null,"status":{"timestamp":"2025-11-15T10:43:12+0100","rCode":200,"bCodeMessage":null,"developerMessage":""}}